waifulabs/__init__.py
waifulabs/asynchronous.py
waifulabs/exception.py
waifulabs/func.py
waifulabs/sync.py
waifulabs/waifu.py
Waifulabs-1.1.1.dist-info/LICENSE
Waifulabs-1.1.1.dist-info/METADATA
Waifulabs-1.1.1.dist-info/WHEEL
Waifulabs-1.1.1.dist-info/top_level.txt
Waifulabs-1.1.1.dist-info/RECORD
