Metadata-Version: 2.1
Name: Waifulabs
Version: 1.1.1
Summary: A unofficial wrapper for WaifuLabs
Home-page: https://github.com/Taromaruu/WaifuLabs
Author: TaromaruYuki
Author-email: taromaruyuki@gmail.com
License: UNKNOWN
Download-URL: https://github.com/Taromaruu/WaifuLabs/releases/
Platform: UNKNOWN
Classifier: Programming Language :: Python :: 3
Classifier: License :: OSI Approved :: MIT License
Classifier: Operating System :: OS Independent
Classifier: Development Status :: 5 - Production/Stable
Requires-Python: >=3.6
Requires-Dist: requests
Requires-Dist: aiohttp
